streamlat/__init__.py
streamlat/metrics.py
streamlat-1.0.1.dist-info/METADATA
streamlat-1.0.1.dist-info/WHEEL
streamlat-1.0.1.dist-info/licenses/License
streamlat-1.0.1.dist-info/RECORD
