Metadata-Version: 2.4
Name: streamlat
Version: 1.0.1
Summary: Low-overhead latency metrics for SSE streaming responses (TTFT, E2E, throughput).
Project-URL: Homepage, https://github.com/aman-panjwani/stream-latency-metrics
Project-URL: Issues, https://github.com/aman-panjwani/stream-latency-metrics/issues
Author: Aman Panjwani
License: MIT License
License-File: License
Keywords: latency,metrics,sse,streaming,ttft
Classifier: License :: OSI Approved :: MIT License
Classifier: Operating System :: OS Independent
Classifier: Programming Language :: Python :: 3
Requires-Python: >=3.9
